metkit/__init__.py
metkit/bin/compare-mars-requests.py
metkit/bin/mars-archive-script
metkit/include/metkit/metkit_config.h
metkit/include/metkit/metkit_ecbuild_config.h
metkit/include/metkit/metkit_version.h
metkit/include/metkit/api/metkit_c.h
metkit/include/metkit/config/LibMetkit.h
metkit/include/metkit/fields/FieldIndex.h
metkit/include/metkit/fields/FieldIndexList.h
metkit/include/metkit/fields/SimpleFieldIndex.h
metkit/include/metkit/hypercube/HyperCube.h
metkit/include/metkit/hypercube/HyperCubePayloaded.h
metkit/include/metkit/mars/BaseProtocol.h
metkit/include/metkit/mars/ClientTask.h
metkit/include/metkit/mars/DHSProtocol.h
metkit/include/metkit/mars/MarsExpandContext.h
metkit/include/metkit/mars/MarsExpension.h
metkit/include/metkit/mars/MarsHandle.h
metkit/include/metkit/mars/MarsLanguage.h
metkit/include/metkit/mars/MarsLocation.h
metkit/include/metkit/mars/MarsParsedRequest.h
metkit/include/metkit/mars/MarsParser.h
metkit/include/metkit/mars/MarsParserContext.h
metkit/include/metkit/mars/MarsRequest.h
metkit/include/metkit/mars/MarsRequestHandle.h
metkit/include/metkit/mars/Param.b
metkit/include/metkit/mars/Param.h
metkit/include/metkit/mars/ParamID.h
metkit/include/metkit/mars/Parameter.h
metkit/include/metkit/mars/Quantile.h
metkit/include/metkit/mars/RequestEnvironment.h
metkit/include/metkit/mars/StepRange.b
metkit/include/metkit/mars/StepRange.h
metkit/include/metkit/mars/StepRangeNormalise.h
metkit/include/metkit/mars/Type.h
metkit/include/metkit/mars/TypeAny.h
metkit/include/metkit/mars/TypeDate.h
metkit/include/metkit/mars/TypeEnum.h
metkit/include/metkit/mars/TypeExpver.h
metkit/include/metkit/mars/TypeFloat.h
metkit/include/metkit/mars/TypeInteger.h
metkit/include/metkit/mars/TypeLowercase.h
metkit/include/metkit/mars/TypeMixed.h
metkit/include/metkit/mars/TypeParam.h
metkit/include/metkit/mars/TypeRange.h
metkit/include/metkit/mars/TypeRegex.h
metkit/include/metkit/mars/TypeTime.h
metkit/include/metkit/mars/TypeToByList.h
metkit-1.12.5.dev0.dist-info/licenses/AUTHORS
metkit-1.12.5.dev0.dist-info/licenses/LICENSE
metkit-1.12.5.dev0.dist-info/METADATA
metkit-1.12.5.dev0.dist-info/WHEEL
metkit-1.12.5.dev0.dist-info/top_level.txt
metkit-1.12.5.dev0.dist-info/RECORD
