Metadata-Version: 2.4
Name: metkit
Version: 1.12.5.dev0
Summary: "metkit"
Author: file: AUTHORS
License-File: LICENSE
License-File: AUTHORS
Requires-Dist: eckitlib<2,>=1.28.5
Dynamic: license-file
Dynamic: requires-dist
